FPGA/user/src/top.v
module top (
    input  wire clk,
    input  wire rst
);
    reg [3:0] led_reg;
    always @(posedge clk) begin
        if (rst) begin
            led_reg <= 4'b0000;
        end else begin
            led_reg <= led_reg + 1;
        end
    end
endmodule

FPGA/user/sim/tb_top.v
`timescale 1ns/1ps

module tb_top;
    reg clk = 0;
    reg rst = 0;

    top uut (
        .clk(clk),
        .rst(rst)
    );

    always #5 clk = ~clk; // 100 MHz 

    initial begin
        $dumpfile("tb_top.vcd");
        $dumpvars(0, tb_top);

        rst = 1;
        #20;
        rst = 0;

        #100;
        $finish;
    end
endmodule

FPGA/tb_top.vcd
$date
	Thu Nov 27 02:05:27 2025
$end
$version
	Icarus Verilog
$end
$timescale
	1ps
$end
$scope module tb_top $end
$var reg 1 ! clk $end
$var reg 1 " rst $end
$scope module uut $end
$var wire 1 ! clk $end
$var wire 1 " rst $end
$var reg 4 # led_reg [3:0] $end
$upscope $end
$upscope $end
$enddefinitions $end
$comment Show the parameter values. $end
$dumpall
$end
#0
$dumpvars
bx #
1"
0!
$end
#5000
b0 #
1!
#10000
0!
#15000
1!
#20000
0!
0"
#25000
b1 #
1!
#30000
0!
#35000
b10 #
1!
#40000
0!
#45000
b11 #
1!
#50000
0!
#55000
b100 #
1!
#60000
0!
#65000
b101 #
1!
#70000
0!
#75000
b110 #
1!
#80000
0!
#85000
b111 #
1!
#90000
0!
#95000
b1000 #
1!
#100000
0!
#105000
b1001 #
1!
#110000
0!
#115000
b1010 #
1!
